{
    "updated_at": 1772052624.464434,
    "planet_states": {
        "Novos": {
            "owner": null,
            "defenders": 700,
            "shields": 2500,
            "credit_balance": 82000,
            "credits_initialized": true,
            "last_credit_interest_time": 0.0,
            "max_shields": 2500,
            "max_defenders": 700,
            "last_defense_regen_time": 0.0
        },
        "Urth": {
            "owner": null,
            "defenders": 450,
            "shields": 720,
            "credit_balance": 196000,
            "credits_initialized": true,
            "last_credit_interest_time": 0.0,
            "max_shields": 720,
            "max_defenders": 450,
            "last_defense_regen_time": 0.0
        },
        "Mastodrun": {
            "owner": null,
            "defenders": 5000,
            "shields": 12000,
            "credit_balance": 756000,
            "credits_initialized": true,
            "last_credit_interest_time": 0.0,
            "max_shields": 12000,
            "max_defenders": 5000,
            "last_defense_regen_time": 0.0
        },
        "Zephyrion": {
            "owner": null,
            "defenders": 2000,
            "shields": 2500,
            "credit_balance": 428000,
            "credits_initialized": true,
            "last_credit_interest_time": 0.0,
            "max_shields": 2500,
            "max_defenders": 2000,
            "last_defense_regen_time": 0.0
        },
        "Nebula Vista": {
            "owner": null,
            "defenders": 500,
            "shields": 1200,
            "credit_balance": 338000,
            "credits_initialized": true,
            "last_credit_interest_time": 0.0,
            "max_shields": 1200,
            "max_defenders": 500,
            "last_defense_regen_time": 0.0
        },
        "Gaianeesh": {
            "owner": null,
            "defenders": 1200,
            "shields": 4500,
            "credit_balance": 574000,
            "credits_initialized": true,
            "last_credit_interest_time": 0.0,
            "max_shields": 4500,
            "max_defenders": 1200,
            "last_defense_regen_time": 0.0
        },
        "Arcaniska": {
            "owner": null,
            "defenders": 1800,
            "shields": 3000,
            "credit_balance": 264000,
            "credits_initialized": true,
            "last_credit_interest_time": 0.0,
            "max_shields": 3000,
            "max_defenders": 1800,
            "last_defense_regen_time": 0.0
        },
        "Titan Station": {
            "owner": null,
            "defenders": 2200,
            "shields": 6500,
            "credit_balance": 112000,
            "credits_initialized": true,
            "last_credit_interest_time": 0.0,
            "max_shields": 6500,
            "max_defenders": 2200,
            "last_defense_regen_time": 0.0
        },
        "Avalon": {
            "owner": null,
            "defenders": 1800,
            "shields": 5000,
            "credit_balance": 242000,
            "credits_initialized": true,
            "last_credit_interest_time": 0.0,
            "max_shields": 5000,
            "max_defenders": 1800,
            "last_defense_regen_time": 0.0
        },
        "Greystoke": {
            "owner": null,
            "defenders": 800,
            "shields": 3500,
            "credit_balance": 146000,
            "credits_initialized": true,
            "last_credit_interest_time": 0.0,
            "max_shields": 3500,
            "max_defenders": 800,
            "last_defense_regen_time": 0.0
        },
        "Shadien": {
            "owner": null,
            "defenders": 1200,
            "shields": 5200,
            "credit_balance": 290000,
            "credits_initialized": true,
            "last_credit_interest_time": 0.0,
            "max_shields": 5200,
            "max_defenders": 1200,
            "last_defense_regen_time": 0.0
        },
        "Celestia": {
            "owner": null,
            "defenders": 8500,
            "shields": 15000,
            "credit_balance": 938000,
            "credits_initialized": true,
            "last_credit_interest_time": 0.0,
            "max_shields": 15000,
            "max_defenders": 8500,
            "last_defense_regen_time": 0.0
        },
        "Aetheria": {
            "owner": null,
            "defenders": 1500,
            "shields": 2800,
            "credit_balance": 386000,
            "credits_initialized": true,
            "last_credit_interest_time": 0.0,
            "max_shields": 2800,
            "max_defenders": 1500,
            "last_defense_regen_time": 0.0
        },
        "Pyrothos": {
            "owner": null,
            "defenders": 450,
            "shields": 1000,
            "credit_balance": 168000,
            "credits_initialized": true,
            "last_credit_interest_time": 0.0,
            "max_shields": 1000,
            "max_defenders": 450,
            "last_defense_regen_time": 0.0
        },
        "Solaris": {
            "owner": null,
            "defenders": 1000,
            "shields": 4000,
            "credit_balance": 642000,
            "credits_initialized": true,
            "last_credit_interest_time": 0.0,
            "max_shields": 4000,
            "max_defenders": 1000,
            "last_defense_regen_time": 0.0
        },
        "Terrarin": {
            "owner": null,
            "defenders": 2200,
            "shields": 6500,
            "credit_balance": 550000,
            "credits_initialized": true,
            "last_credit_interest_time": 0.0,
            "max_shields": 6500,
            "max_defenders": 2200,
            "last_defense_regen_time": 0.0
        },
        "Elysium": {
            "owner": null,
            "defenders": 1600,
            "shields": 3800,
            "credit_balance": 486000,
            "credits_initialized": true,
            "last_credit_interest_time": 0.0,
            "max_shields": 3800,
            "max_defenders": 1600,
            "last_defense_regen_time": 0.0
        },
        "Titanica": {
            "owner": null,
            "defenders": 1100,
            "shields": 4200,
            "credit_balance": 134000,
            "credits_initialized": true,
            "last_credit_interest_time": 0.0,
            "max_shields": 4200,
            "max_defenders": 1100,
            "last_defense_regen_time": 0.0
        },
        "Euphorin": {
            "owner": null,
            "defenders": 3200,
            "shields": 7800,
            "credit_balance": 452000,
            "credits_initialized": true,
            "last_credit_interest_time": 0.0,
            "max_shields": 7800,
            "max_defenders": 3200,
            "last_defense_regen_time": 0.0
        },
        "Aphelion": {
            "owner": null,
            "defenders": 3000,
            "shields": 9000,
            "credit_balance": 158000,
            "credits_initialized": true,
            "last_credit_interest_time": 0.0,
            "max_shields": 9000,
            "max_defenders": 3000,
            "last_defense_regen_time": 0.0
        },
        "Aurora": {
            "owner": null,
            "defenders": 2500,
            "shields": 5500,
            "credit_balance": 362000,
            "credits_initialized": true,
            "last_credit_interest_time": 0.0,
            "max_shields": 5500,
            "max_defenders": 2500,
            "last_defense_regen_time": 0.0
        },
        "Hyperius": {
            "owner": null,
            "defenders": 1900,
            "shields": 6200,
            "credit_balance": 604000,
            "credits_initialized": true,
            "last_credit_interest_time": 0.0,
            "max_shields": 6200,
            "max_defenders": 1900,
            "last_defense_regen_time": 0.0
        },
        "Seraphim Cluster": {
            "owner": null,
            "defenders": 600,
            "shields": 2000,
            "credit_balance": 708000,
            "credits_initialized": true,
            "last_credit_interest_time": 0.0,
            "max_shields": 2000,
            "max_defenders": 600,
            "last_defense_regen_time": 0.0
        },
        "Asterudor": {
            "owner": null,
            "defenders": 2800,
            "shields": 7000,
            "credit_balance": 532000,
            "credits_initialized": true,
            "last_credit_interest_time": 0.0,
            "max_shields": 7000,
            "max_defenders": 2800,
            "last_defense_regen_time": 0.0
        },
        "Atlantiz": {
            "owner": null,
            "defenders": 1800,
            "shields": 4500,
            "credit_balance": 416000,
            "credits_initialized": true,
            "last_credit_interest_time": 0.0,
            "max_shields": 4500,
            "max_defenders": 1800,
            "last_defense_regen_time": 0.0
        },
        "Enerlos": {
            "owner": null,
            "defenders": 3500,
            "shields": 8000,
            "credit_balance": 836000,
            "credits_initialized": true,
            "last_credit_interest_time": 0.0,
            "max_shields": 8000,
            "max_defenders": 3500,
            "last_defense_regen_time": 0.0
        },
        "Zednine": {
            "owner": null,
            "defenders": 15000,
            "shields": 15000,
            "credit_balance": 12100,
            "credits_initialized": true,
            "last_credit_interest_time": 0.0,
            "max_shields": 15000,
            "max_defenders": 15000,
            "last_defense_regen_time": 0.0
        },
        "Infernix": {
            "owner": null,
            "defenders": 1000,
            "shields": 3000,
            "credit_balance": 334000,
            "credits_initialized": true,
            "last_credit_interest_time": 0.0,
            "max_shields": 3000,
            "max_defenders": 1000,
            "last_defense_regen_time": 0.0
        }
    }
}